{
  "pages": [
    {
      "id": "cuanto-cuesta-importar-una-lancha-a-chile",
      "title": "¿Cuánto cuesta importar una lancha?",
      "description": "Conoce los costos detallados de importar tu lancha o embarcación desde USA a Chile.",
      "url": "/cuanto-cuesta-importar-una-lancha-a-chile/",
      "category": "Importación",
      "icon": "money"
    },
    {
      "id": "requisitos-importar-embarcaciones-chile",
      "title": "Requisitos de Importación",
      "description": "Documentos y trámites necesarios para importar legalmente tu embarcación.",
      "url": "/requisitos-importar-embarcaciones-chile/",
      "category": "Documentación",
      "icon": "clipboard"
    },
    {
      "id": "casos-de-importacion",
      "title": "Casos de Éxito",
      "description": "Conoce importaciones reales que hemos realizado con éxito.",
      "url": "/casos-de-importacion/",
      "category": "Casos",
      "icon": "trophy"
    },
    {
      "id": "cotizar-importacion",
      "title": "Cotizar Importación",
      "description": "Solicita tu cotización personalizada gratis sin compromiso.",
      "url": "/cotizar-importacion/",
      "category": "Cotización",
      "icon": "calculator"
    },
    {
      "id": "importacion-lanchas-chile",
      "title": "Importación de Lanchas",
      "description": "Lanchas nuevas y usadas desde USA con servicio integral puerta a puerta.",
      "url": "/importacion-lanchas-chile/",
      "category": "Servicios",
      "icon": "boat"
    },
    {
      "id": "importacion-embarcaciones-usa-chile",
      "title": "Embarcaciones desde USA",
      "description": "Servicio completo de importación USA-Chile para todo tipo de embarcaciones.",
      "url": "/importacion-embarcaciones-usa-chile/",
      "category": "Servicios",
      "icon": "globe"
    },
    {
      "id": "importacion-veleros-chile",
      "title": "Importación de Veleros",
      "description": "Veleros de crucero y regata desde Estados Unidos a Chile.",
      "url": "/importacion-veleros-chile/",
      "category": "Servicios",
      "icon": "sailboat"
    },
    {
      "id": "logistica-maritima-importacion",
      "title": "Logística Marítima",
      "description": "Transporte, documentación y trámites aduaneros para tu embarcación.",
      "url": "/logistica-maritima-importacion/",
      "category": "Logística",
      "icon": "ship"
    },
    {
      "id": "servicios",
      "title": "Todos los Servicios",
      "description": "Conoce todos nuestros servicios de importación náutica.",
      "url": "/servicios/",
      "category": "Servicios",
      "icon": "anchor"
    },
    {
      "id": "como-comprar-lancha-usada-chile",
      "title": "Cómo Comprar una Lancha Usada en Chile",
      "description": "Guía completa con checklist de verificación, documentos necesarios y consejos de expertos.",
      "url": "/como-comprar-lancha-usada-chile/",
      "category": "Compra",
      "icon": "key"
    },
    {
      "id": "como-vender-moto-de-agua-chile",
      "title": "Cómo Vender una Moto de Agua en Chile",
      "description": "Documentos necesarios, cómo fijar el precio y consejos para vender rápido y seguro.",
      "url": "/como-vender-moto-de-agua-chile/",
      "category": "Venta",
      "icon": "jetski"
    },
    {
      "id": "costo-mantener-lancha-chile",
      "title": "Costos de Mantener una Lancha en Chile",
      "description": "Desglose completo de gastos anuales: marina, combustible, seguro, mantenimiento y más.",
      "url": "/costo-mantener-lancha-chile/",
      "category": "Costos",
      "icon": "wrench"
    },
    {
      "id": "documentos-tramites-vender-embarcacion-chile",
      "title": "Documentos y Trámites para Vender Embarcación",
      "description": "Certificados, transferencia ante Autoridad Marítima y requisitos legales actualizados.",
      "url": "/documentos-tramites-vender-embarcacion-chile/",
      "category": "Documentación",
      "icon": "document"
    },
    {
      "id": "embarcaciones-usadas",
      "title": "Embarcaciones Usadas en Chile",
      "description": "Lanchas, veleros, motos de agua y yates. Asesoría experta en compra, venta e importación.",
      "url": "/embarcaciones-usadas/",
      "category": "Catálogo",
      "icon": "tag"
    },
    {
      "id": "importar-motos-de-agua-desde-usa",
      "title": "Importar Motos de Agua desde USA",
      "description": "Costos, trámites aduaneros, homologación y proceso paso a paso para traer tu Jet Ski.",
      "url": "/importar-motos-de-agua-desde-usa/",
      "category": "Importación",
      "icon": "wave"
    },
    {
      "id": "inspeccion-precompra-embarcaciones",
      "title": "Inspección Pre-Compra de Embarcaciones",
      "description": "Qué revisar en casco, motor, sistemas eléctricos y documentación antes de comprar.",
      "url": "/inspeccion-precompra-embarcaciones/",
      "category": "Compra",
      "icon": "search"
    },
    {
      "id": "preguntas-frecuentes-embarcaciones-usadas",
      "title": "Preguntas Frecuentes sobre Embarcaciones",
      "description": "Mega FAQ: documentos, precios, importación y todo sobre lanchas, veleros y motos de agua.",
      "url": "/preguntas-frecuentes-embarcaciones-usadas/",
      "category": "FAQ",
      "icon": "question"
    },
    {
      "id": "seguro-embarcaciones-chile",
      "title": "Seguro para Embarcaciones en Chile",
      "description": "Coberturas obligatorias, todo riesgo, precios y cómo elegir el mejor seguro náutico.",
      "url": "/seguro-embarcaciones-chile/",
      "category": "Seguros",
      "icon": "shield"
    },
    {
      "id": "tipos-de-lanchas-segun-uso",
      "title": "Tipos de Lanchas según Uso",
      "description": "Guía para elegir la mejor lancha para familia, pesca, deportes acuáticos o recreo.",
      "url": "/tipos-de-lanchas-segun-uso/",
      "category": "Guías",
      "icon": "compass"
    },
    {
      "id": "transporte-logistica-embarcaciones-chile",
      "title": "Transporte de Embarcaciones en Chile",
      "description": "Servicios de transporte terrestre y marítimo de lanchas, veleros y motos de agua.",
      "url": "/transporte-logistica-embarcaciones-chile/",
      "category": "Logística",
      "icon": "truck"
    },
    {
      "id": "lanchas",
      "title": "Lanchas en Venta",
      "description": "Encuentra lanchas en venta: nuevas, usadas, importadas desde USA. Asesoría experta.",
      "url": "/lanchas/",
      "category": "Catálogo",
      "icon": "flag"
    },
    {
      "id": "veleros-usados",
      "title": "Veleros Usados en Venta",
      "description": "Veleros usados: crucero, regata y navegación costera. Importación desde USA.",
      "url": "/veleros-usados/",
      "category": "Catálogo",
      "icon": "helm"
    },
    {
      "id": "veleros-usados-a-la-venta-en-chile-o-usa",
      "title": "Veleros Usados: Chile o USA",
      "description": "Guía comparativa para comprar veleros usados en Chile o importar desde USA.",
      "url": "/veleros-usados-a-la-venta-en-chile-o-usa/",
      "category": "Guías",
      "icon": "map"
    },
    {
      "id": "embarcaciones",
      "title": "Embarcaciones en Venta",
      "description": "Todo tipo de embarcaciones: lanchas, veleros, yates, motos de agua. Nuevas, usadas e importadas.",
      "url": "/embarcaciones/",
      "category": "Catálogo",
      "icon": "star"
    },
    {
      "id": "lanchas-de-pesca-usadas",
      "title": "Lanchas de Pesca Usadas",
      "description": "Bass boats, center console y walkaround. Importación desde USA e inspección técnica.",
      "url": "/lanchas-de-pesca-usadas/",
      "category": "Catálogo",
      "icon": "binoculars"
    },
    {
      "id": "botes-de-pesca",
      "title": "Botes de Pesca",
      "description": "Botes de pesca en aluminio y fibra de vidrio. Nuevos y usados para lagos, ríos y costa.",
      "url": "/botes-de-pesca/",
      "category": "Catálogo",
      "icon": "eye"
    },
    {
      "id": "importar-embarcaciones-usa",
      "title": "Importar Embarcaciones desde USA",
      "description": "Guía paso a paso para importar embarcaciones desde Estados Unidos a Chile.",
      "url": "/importar-embarcaciones-usa/",
      "category": "Importación",
      "icon": "globe"
    },
    {
      "id": "servicios-importacion",
      "title": "Servicios de Importación",
      "description": "Servicios completos de importación náutica: búsqueda, inspección, transporte y aduana.",
      "url": "/servicios-importacion/",
      "category": "Servicios",
      "icon": "handshake"
    },
    {
      "id": "comprar-lanchas-usadas-en-chile-o-en-usa",
      "title": "Comprar Lanchas: ¿Chile o USA?",
      "description": "Comparativa completa: comprar lancha usada en Chile vs importar desde USA.",
      "url": "/comprar-lanchas-usadas-en-chile-o-en-usa/",
      "category": "Guías",
      "icon": "bookmark"
    },
    {
      "id": "lanchas-usadas-en-chile-2",
      "title": "Lanchas Usadas en Chile",
      "description": "Catálogo actualizado de lanchas usadas en Chile. Todas las marcas y precios.",
      "url": "/lanchas-usadas-en-chile-2/",
      "category": "Catálogo",
      "icon": "sailboat"
    },
    {
      "id": "lanchas-usadas",
      "title": "Lanchas Usadas",
      "description": "Portal de lanchas usadas: compra, venta e importación. Todas las marcas y tamaños.",
      "url": "/lanchas-usadas/",
      "category": "Catálogo",
      "icon": "list"
    }
  ],
  "categories": [
    "Importación",
    "Servicios",
    "Compra",
    "Venta",
    "Documentación",
    "Costos",
    "Seguros",
    "Logística",
    "Guías",
    "FAQ",
    "Catálogo",
    "Cotización",
    "Casos"
  ]
}
